LICENSE
MANIFEST.in
README.md
setup.cfg
setup.py
podiant_webhooks.egg-info/PKG-INFO
podiant_webhooks.egg-info/SOURCES.txt
podiant_webhooks.egg-info/dependency_links.txt
podiant_webhooks.egg-info/not-zip-safe
podiant_webhooks.egg-info/requires.txt
podiant_webhooks.egg-info/top_level.txt
webhooks/__init__.py
webhooks/admin.py
webhooks/models.py
webhooks/migrations/0001_initial.py
webhooks/migrations/__init__.py