Metadata-Version: 2.1
Name: podiant-webhooks
Version: 0.1.0
Summary: A super-simple, arbitrary webhook client
Home-page: https://git.steadman.io/podiant/webhooks
Author: Mark Steadman
Author-email: mark@podiant.co
License: MIT
Keywords: podiant-webhooks
Platform: UNKNOWN
Classifier: Development Status :: 3 - Alpha
Classifier: Framework :: Django :: 1.11
Classifier: Intended Audience :: Developers
Classifier: License :: OSI Approved :: BSD License
Classifier: Natural Language :: English
Classifier: Programming Language :: Python :: 3
Classifier: Programming Language :: Python :: 3.4
Classifier: Programming Language :: Python :: 3.5
Classifier: Programming Language :: Python :: 3.6
